aratrum/Aratrum.py
aratrum/Config.py
aratrum/__init__.py
aratrum-0.3.2.dist-info/DESCRIPTION.rst
aratrum-0.3.2.dist-info/METADATA
aratrum-0.3.2.dist-info/RECORD
aratrum-0.3.2.dist-info/WHEEL
aratrum-0.3.2.dist-info/metadata.json
aratrum-0.3.2.dist-info/top_level.txt
