Metadata-Version: 2.0
Name: aratrum
Version: 0.3.2
Summary: A simple json configuration handler.
Home-page: https://github.com/Vesuvium/aratrum
Author: Jacopo Cascioli
Author-email: jacopocascioli@gmail.com
License: MIT
Platform: UNKNOWN
Classifier: Intended Audience :: Developers
Classifier: Operating System :: OS Independent
Classifier: Programming Language :: Python :: 3
Classifier: Programming Language :: Python :: 3.5
Classifier: Development Status :: 4 - Beta
Classifier: License :: OSI Approved :: MIT License
Requires-Dist: ujson (>=1.35)
